foundry/__init__.py
foundry/common.py
foundry/constants.py
foundry/version.py
foundry/callbacks/__init__.py
foundry/callbacks/callback.py
foundry/callbacks/health_logging.py
foundry/callbacks/metrics_logging.py
foundry/callbacks/timing_logging.py
foundry/callbacks/train_logging.py
foundry/hydra/resolvers.py
foundry/inference_engines/base.py
foundry/inference_engines/checkpoint_registry.py
foundry/metrics/__init__.py
foundry/metrics/losses.py
foundry/metrics/metric.py
foundry/model/layers/blocks.py
foundry/testing/__init__.py
foundry/testing/fixtures.py
foundry/testing/pytest_hooks.py
foundry/trainers/fabric.py
foundry/training/EMA.py
foundry/training/checkpoint.py
foundry/training/schedulers.py
foundry/utils/alignment.py
foundry/utils/components.py
foundry/utils/datasets.py
foundry/utils/ddp.py
foundry/utils/instantiators.py
foundry/utils/logging.py
foundry/utils/rigid.py
foundry/utils/rotation_augmentation.py
foundry/utils/squashfs.py
foundry/utils/torch.py
foundry/utils/weights.py
foundry_cli/__init__.py
foundry_cli/download_checkpoints.py
mpnn/__init__.py
mpnn/inference.py
mpnn/train.py
mpnn/collate/feature_collator.py
mpnn/inference_engines/mpnn.py
mpnn/loss/nll_loss.py
mpnn/metrics/nll.py
mpnn/metrics/sequence_recovery.py
mpnn/model/mpnn.py
mpnn/model/layers/graph_embeddings.py
mpnn/model/layers/message_passing.py
mpnn/model/layers/position_wise_feed_forward.py
mpnn/model/layers/positional_encoding.py
mpnn/pipelines/mpnn.py
mpnn/samplers/samplers.py
mpnn/trainers/mpnn.py
mpnn/transforms/polymer_ligand_interface.py
mpnn/transforms/feature_aggregation/mpnn.py
mpnn/transforms/feature_aggregation/polymer_ligand_interface.py
mpnn/transforms/feature_aggregation/token_encodings.py
mpnn/transforms/feature_aggregation/user_settings.py
mpnn/utils/inference.py
mpnn/utils/probability.py
mpnn/utils/weights.py
rf3/__init__.py
rf3/_version.py
rf3/alignment.py
rf3/chemical.py
rf3/cli.py
rf3/inference.py
rf3/kinematics.py
rf3/scoring.py
rf3/train.py
rf3/util_module.py
rc_foundry-0.1.9.dist-info/METADATA
rc_foundry-0.1.9.dist-info/WHEEL
rc_foundry-0.1.9.dist-info/entry_points.txt
rc_foundry-0.1.9.dist-info/licenses/LICENSE.md
rc_foundry-0.1.9.dist-info/RECORD
