Metadata-Version: 2.4
Name: rc-foundry
Version: 0.1.9
Summary: Shared utilities and training infrastructure for biomolecular structure prediction models.
Author-email: Institute for Protein Design <contact@ipd.uw.edu>
License: BSD 3-Clause License
License-File: LICENSE.md
Classifier: Intended Audience :: Developers
Classifier: Intended Audience :: Science/Research
Classifier: License :: OSI Approved :: BSD License
Classifier: Natural Language :: English
Classifier: Operating System :: MacOS
Classifier: Operating System :: Microsoft :: Windows
Classifier: Operating System :: POSIX :: Linux
Classifier: Programming Language :: Python :: 3
Classifier: Programming Language :: Python :: Implementation :: CPython
Classifier: Topic :: Scientific/Engineering :: Bio-Informatics
Requires-Python: >=3.12
Requires-Dist: assertpy
Requires-Dist: atomworks[ml]>=2.1.1
Requires-Dist: beartype<1,>=0.18.0
Requires-Dist: dm-tree<1,>=0.1.6
Requires-Dist: einops<1,>=0.8.0
Requires-Dist: einx<1,>=0.1.0
Requires-Dist: environs<12,>=11.0.0
Requires-Dist: hydra-core<1.4,>=1.3.0
Requires-Dist: ipykernel>=6.31.0
Requires-Dist: jaxtyping<1,>=0.2.17
Requires-Dist: lightning>=2.5.0
Requires-Dist: loralib>=0.1.1
Requires-Dist: opt-einsum<4,>=3.4.0
Requires-Dist: pandas
Requires-Dist: rich>=13.9.4
Requires-Dist: rootutils<1.1,>=1.0.7
Requires-Dist: toolz
Requires-Dist: torch<3,>=2.2.0
Requires-Dist: typer<1,>=0.20.0
Requires-Dist: wandb<1,>=0.15.10
Requires-Dist: zstandard
Provides-Extra: all
Requires-Dist: cuequivariance-ops-cu12>=0.6.1; (sys_platform == 'linux') and extra == 'all'
Requires-Dist: cuequivariance-ops-torch-cu12>=0.6.1; (sys_platform == 'linux') and extra == 'all'
Requires-Dist: cuequivariance-torch>=0.6.1; (sys_platform == 'linux') and extra == 'all'
Requires-Dist: pydantic>=2.8; extra == 'all'
Provides-Extra: dev
Requires-Dist: assertpy; extra == 'dev'
Requires-Dist: atomworks[dev,ml,openbabel]>=2.1.1; extra == 'dev'
Requires-Dist: debugpy<2,>=1.8.5; extra == 'dev'
Requires-Dist: ipdb; extra == 'dev'
Requires-Dist: ipykernel<7,>=6.29.4; extra == 'dev'
Requires-Dist: pre-commit; extra == 'dev'
Requires-Dist: pytest-benchmark<6,>=5.0.0; extra == 'dev'
Requires-Dist: pytest-cov<5,>=4.1.0; extra == 'dev'
Requires-Dist: pytest-dotenv<1,>=0.5.2; extra == 'dev'
Requires-Dist: pytest-testmon<3,>=2.1.1; extra == 'dev'
Requires-Dist: pytest-xdist<4,>=3.6.1; extra == 'dev'
Requires-Dist: pytest<9,>=8.2.0; extra == 'dev'
Requires-Dist: ruff==0.8.3; extra == 'dev'
Provides-Extra: rf3
Requires-Dist: cuequivariance-ops-cu12>=0.6.1; (sys_platform == 'linux') and extra == 'rf3'
Requires-Dist: cuequivariance-ops-torch-cu12>=0.6.1; (sys_platform == 'linux') and extra == 'rf3'
Requires-Dist: cuequivariance-torch>=0.6.1; (sys_platform == 'linux') and extra == 'rf3'
Provides-Extra: rfd3
Requires-Dist: pydantic>=2.8; extra == 'rfd3'
